ipaddr_ext
mignis
