Metadata-Version: 1.1
Name: mignis
Version: 0.9.5.post1
Summary: Mignis is a semantic based tool for firewall configuration
Home-page: https://github.com/segroup/Mignis
Author: UNKNOWN
Author-email: UNKNOWN
License: MIT
Keywords: iptables,firewall,semantic firewall configuration,netfilter
Platform: UNKNOWN
Classifier: Development Status :: 4 - Beta
Classifier: Environment :: Console
Classifier: License :: OSI Approved :: MIT License
Classifier: Natural Language :: English
Classifier: Operating System :: POSIX :: Linux
Classifier: Programming Language :: Python :: 2
Classifier: Programming Language :: Python :: 3
Classifier: Topic :: Security
Classifier: Topic :: System :: Networking :: Firewalls
